dataframe_schema_sync/__init__.py
dataframe_schema_sync/py.typed
dataframe_schema_sync/schema_inference.py
dataframe_schema_sync-0.21.6.dist-info/licenses/LICENSE
dataframe_schema_sync-0.21.6.dist-info/METADATA
dataframe_schema_sync-0.21.6.dist-info/WHEEL
dataframe_schema_sync-0.21.6.dist-info/top_level.txt
dataframe_schema_sync-0.21.6.dist-info/RECORD
