Metadata-Version: 2.4
Name: dataframe-schema-sync
Version: 0.21.6
Summary: This package will read a dataframe and will infer data types while storing the structure for later retrieval
Author-email: Mark Moreno <mark@securehst.com>
License: MIT
Project-URL: Bug Tracker, https://github.com/markm-io/dataframe-schema-sync/issues
Project-URL: Changelog, https://github.com/markm-io/dataframe-schema-sync/blob/main/CHANGELOG.md
Project-URL: documentation, https://dataframe-schema-sync.readthedocs.io
Project-URL: repository, https://github.com/markm-io/dataframe-schema-sync
Classifier: Development Status :: 2 - Pre-Alpha
Classifier: Intended Audience :: Developers
Classifier: Natural Language :: English
Classifier: Operating System :: OS Independent
Classifier: Programming Language :: Python :: 3.10
Classifier: Programming Language :: Python :: 3.11
Classifier: Programming Language :: Python :: 3.12
Classifier: Programming Language :: Python :: 3.13
Classifier: Topic :: Software Development :: Libraries
Requires-Python: >=3.10
License-File: LICENSE
Requires-Dist: pandas>=2.2.3
Requires-Dist: psycopg2-binary>=2.9.10
Requires-Dist: pyjanitor>=0.30.0
Requires-Dist: pyyaml>=6.0.2
Requires-Dist: sqlalchemy>=2.0.37
Dynamic: license-file
